{
  "nav": [
    {
      "text": "架构基础",
      "items": [
        {
          "text": "Node",
          "link": "/views/架构基础/Node/readme.md"
        },
        {
          "text": "SSG",
          "link": "/views/架构基础/SSG/readme.md"
        },
        {
          "text": "SSR",
          "link": "/views/架构基础/SSR/readme.md"
        },
        {
          "text": "数据库",
          "link": "/views/架构基础/数据库/readme.md"
        },
        {
          "text": "数据缓存",
          "link": "/views/架构基础/数据缓存/readme.md"
        },
        {
          "text": "编程语言",
          "link": "/views/架构基础/编程语言/readme.md"
        },
        {
          "text": "网页服务器",
          "link": "/views/架构基础/网页服务器/readme.md"
        }
      ]
    }
  ],
  "sidebar": {
    "/views/架构基础/Node": [
      {
        "text": "Node",
        "collapsed": false,
        "items": [
          {
            "text": "EventEmitter",
            "link": "/views/架构基础/Node/EventEmitter"
          },
          {
            "text": "Node 概述",
            "link": "/views/架构基础/Node/Node 概述"
          },
          {
            "text": "http 模块",
            "link": "/views/架构基础/Node/http 模块"
          },
          {
            "text": "https 模块",
            "link": "/views/架构基础/Node/https 模块"
          },
          {
            "text": "net 模块",
            "link": "/views/架构基础/Node/net 模块"
          },
          {
            "text": "事件循环",
            "link": "/views/架构基础/Node/事件循环"
          },
          {
            "text": "全局对象",
            "link": "/views/架构基础/Node/全局对象"
          },
          {
            "text": "基本内置模块",
            "link": "/views/架构基础/Node/基本内置模块"
          },
          {
            "text": "常用库",
            "items": [
              {
                "text": "connect-history-api-fallback",
                "link": "/views/架构基础/Node/常用库/connect-history-api-fallback"
              },
              {
                "text": "express",
                "link": "/views/架构基础/Node/常用库/express"
              },
              {
                "text": "qs",
                "link": "/views/架构基础/Node/常用库/qs"
              }
            ],
            "collapsed": false
          },
          {
            "text": "文件IO",
            "link": "/views/架构基础/Node/文件IO"
          },
          {
            "text": "模块化",
            "link": "/views/架构基础/Node/模块化"
          },
          {
            "text": "生命周期",
            "link": "/views/架构基础/Node/生命周期"
          }
        ]
      }
    ],
    "/views/架构基础/SSG": [
      {
        "text": "SSG",
        "collapsed": false,
        "items": [
          {
            "text": "VitePress",
            "items": [
              {
                "text": "创建一个VitePress插件",
                "link": "/views/架构基础/SSG/VitePress/创建一个VitePress插件"
              },
              {
                "text": "部署 VitePress 站点",
                "link": "/views/架构基础/SSG/VitePress/部署 VitePress 站点"
              }
            ],
            "collapsed": false
          }
        ]
      }
    ],
    "/views/架构基础/SSR": [
      {
        "text": "SSR",
        "collapsed": false,
        "items": [
          {
            "text": "React SSR",
            "items": [
              {
                "text": "CSR与SSR",
                "link": "/views/架构基础/SSR/React SSR/CSR与SSR"
              },
              {
                "text": "NextJS",
                "items": [
                  {
                    "text": "NextJS 概述",
                    "link": "/views/架构基础/SSR/React SSR/NextJS/NextJS 概述"
                  },
                  {
                    "text": "api 代理",
                    "link": "/views/架构基础/SSR/React SSR/NextJS/api 代理"
                  },
                  {
                    "text": "cookie和header转换",
                    "link": "/views/架构基础/SSR/React SSR/NextJS/cookie和header转换"
                  },
                  {
                    "text": "使用redux",
                    "link": "/views/架构基础/SSR/React SSR/NextJS/使用redux"
                  },
                  {
                    "text": "动态路由静态化",
                    "link": "/views/架构基础/SSR/React SSR/NextJS/动态路由静态化"
                  },
                  {
                    "text": "引入样式",
                    "link": "/views/架构基础/SSR/React SSR/NextJS/引入样式"
                  },
                  {
                    "text": "数据静态化",
                    "link": "/views/架构基础/SSR/React SSR/NextJS/数据静态化"
                  },
                  {
                    "text": "模板",
                    "link": "/views/架构基础/SSR/React SSR/NextJS/模板"
                  },
                  {
                    "text": "自定义页面",
                    "link": "/views/架构基础/SSR/React SSR/NextJS/自定义页面"
                  },
                  {
                    "text": "请求数据",
                    "link": "/views/架构基础/SSR/React SSR/NextJS/请求数据"
                  },
                  {
                    "text": "路由",
                    "link": "/views/架构基础/SSR/React SSR/NextJS/路由"
                  },
                  {
                    "text": "静态化",
                    "link": "/views/架构基础/SSR/React SSR/NextJS/静态化"
                  },
                  {
                    "text": "静态资源",
                    "link": "/views/架构基础/SSR/React SSR/NextJS/静态资源"
                  },
                  {
                    "text": "页面信息",
                    "link": "/views/架构基础/SSR/React SSR/NextJS/页面信息"
                  }
                ],
                "collapsed": false
              },
              {
                "text": "staticContext",
                "link": "/views/架构基础/SSR/React SSR/staticContext"
              },
              {
                "text": "使用Redux",
                "link": "/views/架构基础/SSR/React SSR/使用Redux"
              },
              {
                "text": "使用路由",
                "link": "/views/架构基础/SSR/React SSR/使用路由"
              },
              {
                "text": "引入图片",
                "link": "/views/架构基础/SSR/React SSR/引入图片"
              },
              {
                "text": "引入样式",
                "link": "/views/架构基础/SSR/React SSR/引入样式"
              },
              {
                "text": "数据通信",
                "link": "/views/架构基础/SSR/React SSR/数据通信"
              },
              {
                "text": "渲染组件",
                "link": "/views/架构基础/SSR/React SSR/渲染组件"
              }
            ],
            "collapsed": false
          },
          {
            "text": "React SSR",
            "link": "/views/架构基础/SSR/React SSR"
          },
          {
            "text": "SSR 概述",
            "link": "/views/架构基础/SSR/SSR 概述"
          },
          {
            "text": "Vue SSR",
            "items": [
              {
                "text": "NuxtJS",
                "items": [
                  {
                    "text": "Nuxt 布局",
                    "link": "/views/架构基础/SSR/Vue SSR/NuxtJS/Nuxt 布局"
                  },
                  {
                    "text": "Nuxt 路由",
                    "link": "/views/架构基础/SSR/Vue SSR/NuxtJS/Nuxt 路由"
                  },
                  {
                    "text": "Nuxt 静态化",
                    "link": "/views/架构基础/SSR/Vue SSR/NuxtJS/Nuxt 静态化"
                  },
                  {
                    "text": "NuxtJS",
                    "link": "/views/架构基础/SSR/Vue SSR/NuxtJS/NuxtJS"
                  },
                  {
                    "text": "vuex 应用",
                    "link": "/views/架构基础/SSR/Vue SSR/NuxtJS/vuex 应用"
                  },
                  {
                    "text": "引入Element-ui",
                    "link": "/views/架构基础/SSR/Vue SSR/NuxtJS/引入Element-ui"
                  },
                  {
                    "text": "引入Vuetify",
                    "link": "/views/架构基础/SSR/Vue SSR/NuxtJS/引入Vuetify"
                  },
                  {
                    "text": "鉴权应用",
                    "link": "/views/架构基础/SSR/Vue SSR/NuxtJS/鉴权应用"
                  }
                ],
                "collapsed": false
              },
              {
                "text": "SSR 环境搭建",
                "link": "/views/架构基础/SSR/Vue SSR/SSR 环境搭建"
              },
              {
                "text": "Vue SSR",
                "link": "/views/架构基础/SSR/Vue SSR/Vue SSR"
              },
              {
                "text": "vue-cli 构建SSR",
                "link": "/views/架构基础/SSR/Vue SSR/vue-cli 构建SSR"
              },
              {
                "text": "数据预取",
                "link": "/views/架构基础/SSR/Vue SSR/数据预取"
              },
              {
                "text": "路由处理",
                "link": "/views/架构基础/SSR/Vue SSR/路由处理"
              }
            ],
            "collapsed": false
          },
          {
            "text": "基本API",
            "link": "/views/架构基础/SSR/基本API"
          },
          {
            "text": "服务端与客户端",
            "link": "/views/架构基础/SSR/服务端与客户端"
          },
          {
            "text": "静态资源服务器",
            "link": "/views/架构基础/SSR/静态资源服务器"
          }
        ]
      }
    ],
    "/views/架构基础/数据库": [
      {
        "text": "数据库",
        "collapsed": false,
        "items": [
          {
            "text": "NoSQL",
            "items": [
              {
                "text": "CouchDB",
                "link": "/views/架构基础/数据库/NoSQL/CouchDB"
              },
              {
                "text": "Hbase",
                "link": "/views/架构基础/数据库/NoSQL/Hbase"
              },
              {
                "text": "MongoDB",
                "link": "/views/架构基础/数据库/NoSQL/MongoDB"
              }
            ],
            "collapsed": false
          },
          {
            "text": "SQL",
            "items": [
              {
                "text": "DB2",
                "link": "/views/架构基础/数据库/SQL/DB2"
              },
              {
                "text": "MySQL",
                "link": "/views/架构基础/数据库/SQL/MySQL"
              },
              {
                "text": "Oracle",
                "link": "/views/架构基础/数据库/SQL/Oracle"
              },
              {
                "text": "PostgreSQL",
                "link": "/views/架构基础/数据库/SQL/PostgreSQL"
              },
              {
                "text": "SQL Server",
                "link": "/views/架构基础/数据库/SQL/SQL Server"
              }
            ],
            "collapsed": false
          }
        ]
      }
    ],
    "/views/架构基础/数据缓存": [
      {
        "text": "数据缓存",
        "collapsed": false,
        "items": [
          {
            "text": "Memcached",
            "link": "/views/架构基础/数据缓存/Memcached"
          },
          {
            "text": "Redis",
            "link": "/views/架构基础/数据缓存/Redis"
          }
        ]
      }
    ],
    "/views/架构基础/编程语言": [
      {
        "text": "编程语言",
        "collapsed": false,
        "items": []
      }
    ],
    "/views/架构基础/网页服务器": [
      {
        "text": "网页服务器",
        "collapsed": false,
        "items": [
          {
            "text": "Apache",
            "link": "/views/架构基础/网页服务器/Apache"
          },
          {
            "text": "Nginx",
            "link": "/views/架构基础/网页服务器/Nginx"
          },
          {
            "text": "Tomcat",
            "link": "/views/架构基础/网页服务器/Tomcat"
          }
        ]
      }
    ]
  }
}